tfae/__init__.py
tfae/bottlenecks/__init__.py
tfae/bottlenecks/base.py
tfae/bottlenecks/bernoulli.py
tfae/bottlenecks/gaussian.py
tfae/bottlenecks/vanilla.py
tfae/bottlenecks/variational.py
tfae/models/__init__.py
tfae/models/autoencoder.py
tfae/models/deep.py
tfae/regularizers/__init__.py
tfae/regularizers/base.py
tfae/regularizers/gaussian.py
tfae/regularizers/l2.py
tfae/schedulers/__init__.py
tfae/schedulers/base.py
tfae/schedulers/dasr.py
tfae/utils.py
tfae-1.0.2.dist-info/LICENSE
tfae-1.0.2.dist-info/WHEEL
tfae-1.0.2.dist-info/METADATA
tfae-1.0.2.dist-info/RECORD
