Metadata-Version: 2.1
Name: tfae
Version: 1.0.2
Summary: TFAE it's a TensorFlow extension for building and training different types of autoencoders
Home-page: https://github.com/arlegotin/TFAE
License: Apache-2.0
Keywords: tensorflow,autoencoder,variational
Author: Artem Legotin
Author-email: hello@artemlegotin.com
Requires-Python: >=3.7,<=3.10
Classifier: License :: OSI Approved :: Apache Software License
Classifier: Programming Language :: Python :: 3
Classifier: Programming Language :: Python :: 3.10
Classifier: Programming Language :: Python :: 3.7
Classifier: Programming Language :: Python :: 3.8
Classifier: Programming Language :: Python :: 3.9
Requires-Dist: tensorflow (>=2.9.1,<3.0.0)
Project-URL: Repository, https://github.com/arlegotin/TFAE
